{
  "updated_at": "2026-06-13T03:01:48.414427Z",
  "activities": [
    {
      "resource_state": 2,
      "athlete": {
        "id": 7234187,
        "resource_state": 1
      },
      "name": "Prince Alfred \ud83e\udd34\ud83e\ude72\ud83c\udfca\ud83c\udffb\u200d\u2642\ufe0f",
      "distance": 2000.0,
      "moving_time": 2637,
      "elapsed_time": 2637,
      "total_elevation_gain": 0,
      "type": "Swim",
      "sport_type": "Swim",
      "device_name": "Apple Watch Series 9",
      "id": 18747938433,
      "start_date": "2026-05-31T20:08:52Z",
      "start_date_local": "2026-06-01T06:08:52Z",
      "timezone": "(GMT+10:00) Antarctica/DumontDUrville",
      "utc_offset": 36000.0,
      "location_city": null,
      "location_state": null,
      "location_country": null,
      "achievement_count": 0,
      "kudos_count": 2,
      "comment_count": 0,
      "athlete_count": 1,
      "photo_count": 0,
      "map": {
        "id": "a18747938433",
        "summary_polyline": "",
        "resource_state": 2
      },
      "trainer": true,
      "commute": false,
      "manual": false,
      "private": false,
      "visibility": "followers_only",
      "flagged": false,
      "gear_id": null,
      "start_latlng": [],
      "end_latlng": [],
      "average_speed": 0.758,
      "max_speed": 10.0,
      "has_heartrate": true,
      "average_heartrate": 134.1,
      "max_heartrate": 158.0,
      "heartrate_opt_out": false,
      "display_hide_heartrate_option": true,
      "elev_high": 0.0,
      "elev_low": 0.0,
      "upload_id": 19857468522,
      "upload_id_str": "19857468522",
      "external_id": "F7E7300D-B9AC-4800-9524-5D56CA2AF04F.fit",
      "from_accepted_tag": false,
      "pr_count": 0,
      "total_photo_count": 0,
      "has_kudoed": false,
      "suffer_score": 62.0
    },
    {
      "resource_state": 2,
      "athlete": {
        "id": 7234187,
        "resource_state": 1
      },
      "name": "Prince Alfred \ud83e\udd34\ud83e\ude72\ud83c\udfca\ud83c\udffb\u200d\u2642\ufe0f",
      "distance": 2000.0,
      "moving_time": 2410,
      "elapsed_time": 2410,
      "total_elevation_gain": 0,
      "type": "Swim",
      "sport_type": "Swim",
      "device_name": "Apple Watch Series 9",
      "id": 18747938424,
      "start_date": "2026-06-01T20:04:48Z",
      "start_date_local": "2026-06-02T06:04:48Z",
      "timezone": "(GMT+10:00) Antarctica/DumontDUrville",
      "utc_offset": 36000.0,
      "location_city": null,
      "location_state": null,
      "location_country": null,
      "achievement_count": 0,
      "kudos_count": 2,
      "comment_count": 0,
      "athlete_count": 1,
      "photo_count": 0,
      "map": {
        "id": "a18747938424",
        "summary_polyline": "",
        "resource_state": 2
      },
      "trainer": true,
      "commute": false,
      "manual": false,
      "private": false,
      "visibility": "followers_only",
      "flagged": false,
      "gear_id": null,
      "start_latlng": [],
      "end_latlng": [],
      "average_speed": 0.83,
      "max_speed": 10.0,
      "has_heartrate": true,
      "average_heartrate": 151.3,
      "max_heartrate": 170.0,
      "heartrate_opt_out": false,
      "display_hide_heartrate_option": true,
      "elev_high": 0.0,
      "elev_low": 0.0,
      "upload_id": 19857468575,
      "upload_id_str": "19857468575",
      "external_id": "B47204C6-A70E-458F-9314-40F761FEF0E0.fit",
      "from_accepted_tag": false,
      "pr_count": 0,
      "total_photo_count": 0,
      "has_kudoed": false,
      "suffer_score": 110.0
    },
    {
      "resource_state": 2,
      "athlete": {
        "id": 7234187,
        "resource_state": 1
      },
      "name": "Prince Alfred \ud83e\udd34\ud83c\udfca\ud83c\udffb\u200d\u2642\ufe0f\ud83e\ude72",
      "distance": 2000.0,
      "moving_time": 2393,
      "elapsed_time": 2393,
      "total_elevation_gain": 0,
      "type": "Swim",
      "sport_type": "Swim",
      "device_name": "Apple Watch Series 9",
      "id": 18766944730,
      "start_date": "2026-06-02T20:05:41Z",
      "start_date_local": "2026-06-03T06:05:41Z",
      "timezone": "(GMT+10:00) Antarctica/DumontDUrville",
      "utc_offset": 36000.0,
      "location_city": null,
      "location_state": null,
      "location_country": null,
      "achievement_count": 0,
      "kudos_count": 2,
      "comment_count": 0,
      "athlete_count": 1,
      "photo_count": 0,
      "map": {
        "id": "a18766944730",
        "summary_polyline": "",
        "resource_state": 2
      },
      "trainer": true,
      "commute": false,
      "manual": false,
      "private": false,
      "visibility": "followers_only",
      "flagged": false,
      "gear_id": null,
      "start_latlng": [],
      "end_latlng": [],
      "average_speed": 0.836,
      "max_speed": 10.0,
      "has_heartrate": true,
      "average_heartrate": 146.2,
      "max_heartrate": 172.0,
      "heartrate_opt_out": false,
      "display_hide_heartrate_option": true,
      "elev_high": 0.0,
      "elev_low": 0.0,
      "upload_id": 19876807736,
      "upload_id_str": "19876807736",
      "external_id": "87C52EC8-C6AB-4C27-A29E-DBB85322C719.fit",
      "from_accepted_tag": false,
      "pr_count": 0,
      "total_photo_count": 0,
      "has_kudoed": false,
      "suffer_score": 92.0
    },
    {
      "resource_state": 2,
      "athlete": {
        "id": 7234187,
        "resource_state": 1
      },
      "name": "Prince Alfred \ud83e\udd34\ud83e\ude72\ud83c\udfca\ud83c\udffb\u200d\u2642\ufe0f",
      "distance": 2000.0,
      "moving_time": 2468,
      "elapsed_time": 2468,
      "total_elevation_gain": 0,
      "type": "Swim",
      "sport_type": "Swim",
      "device_name": "Apple Watch Series 9",
      "id": 18802138932,
      "start_date": "2026-06-03T20:05:38Z",
      "start_date_local": "2026-06-04T06:05:38Z",
      "timezone": "(GMT+10:00) Antarctica/DumontDUrville",
      "utc_offset": 36000.0,
      "location_city": null,
      "location_state": null,
      "location_country": null,
      "achievement_count": 0,
      "kudos_count": 1,
      "comment_count": 0,
      "athlete_count": 1,
      "photo_count": 0,
      "map": {
        "id": "a18802138932",
        "summary_polyline": "",
        "resource_state": 2
      },
      "trainer": true,
      "commute": false,
      "manual": false,
      "private": false,
      "visibility": "followers_only",
      "flagged": false,
      "gear_id": null,
      "start_latlng": [],
      "end_latlng": [],
      "average_speed": 0.81,
      "max_speed": 10.0,
      "has_heartrate": true,
      "average_heartrate": 152.1,
      "max_heartrate": 171.0,
      "heartrate_opt_out": false,
      "display_hide_heartrate_option": true,
      "elev_high": 0.0,
      "elev_low": 0.0,
      "upload_id": 19912635789,
      "upload_id_str": "19912635789",
      "external_id": "414C2CF7-53B3-4B21-BCA5-F5FECA898463.fit",
      "from_accepted_tag": false,
      "pr_count": 0,
      "total_photo_count": 0,
      "has_kudoed": false,
      "suffer_score": 111.0
    },
    {
      "resource_state": 2,
      "athlete": {
        "id": 7234187,
        "resource_state": 1
      },
      "name": "Balmoral buoys \ud83d\udedf \ud83e\ude72\ud83c\udfca\ud83c\udffb\u200d\u2642\ufe0f",
      "distance": 992.4,
      "moving_time": 1348,
      "elapsed_time": 1348,
      "total_elevation_gain": 52.4,
      "type": "Swim",
      "sport_type": "Swim",
      "device_name": "Apple Watch Series 9",
      "id": 18802139460,
      "start_date": "2026-06-04T20:46:07Z",
      "start_date_local": "2026-06-05T06:46:07Z",
      "timezone": "(GMT+10:00) Australia/Sydney",
      "utc_offset": 36000.0,
      "location_city": null,
      "location_state": null,
      "location_country": null,
      "achievement_count": 1,
      "kudos_count": 2,
      "comment_count": 0,
      "athlete_count": 1,
      "photo_count": 0,
      "map": {
        "id": "a18802139460",
        "summary_polyline": "`{mmEundz[a@a@ABa@WK?OMOCKBKGK@?EEAKBGHOBELKFI@ABa@?QDEDSEK@o@Ib@HABW]CDIB?@SJ@BKLKDUBCCEB@@K@EDIAYTGGK?IEO@ABSACBKGo@hCJMPo@?SEGBMHI?K@OL@JD@AD@BCFFHGL@?CJ?FEHDREDGHBDCH?HKRBFCJB@CRCFEJ@DCH@HCFHJBQOn@@\\CJ?@GJ@@DDELE`@?FCLBBFD@D??ANADERFFCFHDIJDFAEAF?B@BFPFRT",
        "resource_state": 2
      },
      "trainer": false,
      "commute": false,
      "manual": false,
      "private": false,
      "visibility": "followers_only",
      "flagged": false,
      "gear_id": null,
      "start_latlng": [
        -33.827208,
        151.252438
      ],
      "end_latlng": [
        -33.827308,
        151.252425
      ],
      "average_speed": 0.736,
      "max_speed": 4.516,
      "has_heartrate": true,
      "average_heartrate": 97.6,
      "max_heartrate": 123.0,
      "heartrate_opt_out": false,
      "display_hide_heartrate_option": true,
      "elev_high": 7.6,
      "elev_low": -5.8,
      "upload_id": 19912636244,
      "upload_id_str": "19912636244",
      "external_id": "F9A919E9-ED43-4FFF-849C-3FDC2A4FC95D.fit",
      "from_accepted_tag": false,
      "pr_count": 0,
      "total_photo_count": 0,
      "has_kudoed": false,
      "suffer_score": 3.0
    },
    {
      "resource_state": 2,
      "athlete": {
        "id": 7234187,
        "resource_state": 1
      },
      "name": "St Leonards Run \ud83c\udfc3\ud83c\udffb\u200d\u2642\ufe0f",
      "distance": 8588.4,
      "moving_time": 2722,
      "elapsed_time": 2797,
      "total_elevation_gain": 124.4,
      "type": "Run",
      "sport_type": "Run",
      "workout_type": null,
      "device_name": "Apple Watch Series 9",
      "id": 18802139873,
      "start_date": "2026-06-05T21:02:03Z",
      "start_date_local": "2026-06-06T07:02:03Z",
      "timezone": "(GMT+10:00) Australia/Sydney",
      "utc_offset": 36000.0,
      "location_city": null,
      "location_state": null,
      "location_country": null,
      "achievement_count": 1,
      "kudos_count": 6,
      "comment_count": 0,
      "athlete_count": 3,
      "photo_count": 0,
      "map": {
        "id": "a18802139873",
        "summary_polyline": "hmnmEkc~y[CJGJOFOBu@Cu@Mo@Du@\\KHCDQrAUx@a@jBoA`EKh@KrAEz@Ip@Cp@UjAs@zHG~A?r@IjAC`BIt@Q~@Ep@GR]b@MHmBU]Ca@BGDAD@DFHZFR@^Cx@Dp@JTJ@Rc@tDC`BMzACtAGdAYxCUvCQzAYjEk@tFe@fHHqCFs@WjDERIJO?eBSm@O_AGsDg@kAGWJQ@gAY]@WAGFCJa@nFQjAE^?TA@mAAm@BWF]PWFkBCu@B[DeA\\c@DS?yAU}@?aBYcBS[G_A_@o@KCEFAH@rA^RLHR?`@Ix@Ev@@RL\\?LWvBIbAGjA@lAHLHJNDn@H`@JHLCHEFWRIJSb@Eb@?h@[zE@d@A\\U~BI~CAf@Fv@?hBHTVZ\\l@DHARIJy@n@uBtA{@d@FOZ[j@e@b@a@x@i@jAo@b@Ml@a@~@Y^GtAMz@Mt@E`BSNCVMFAx@Ez@?n@O^Ad@KbAIl@KPAPBXAJCPULKdAg@FIMi@Eu@Ik@@_ABe@ISBGDu@Ey@@UDU`@_AFS?UGq@BGZYx@e@t@m@z@g@hAmAZYTO^GZSZ[`@k@r@k@|@}@|@k@|@_@pAeAb@W^WX[HOD[CoANqCL}@P}Bh@uHv@sIDaAlAkNGG[GcAGa@GSQWKg@Ic@MyA]rH~@^BNAFKN}CViCTsDJy@J}A?SFYBw@Hq@?OGAg@AOCIGQYM[I_@C[A{ADu@P}Ah@gCJ_CTmCF_@Zw@T{@LgAJa@Xw@h@y@v@gBEe@IK[OEICS@q@AQ",
        "resource_state": 2
      },
      "trainer": false,
      "commute": false,
      "manual": false,
      "private": false,
      "visibility": "followers_only",
      "flagged": false,
      "gear_id": null,
      "start_latlng": [
        -33.830125,
        151.219905
      ],
      "end_latlng": [
        -33.830075,
        151.220222
      ],
      "average_speed": 3.155,
      "max_speed": 5.34,
      "has_heartrate": true,
      "average_heartrate": 155.8,
      "max_heartrate": 184.0,
      "heartrate_opt_out": false,
      "display_hide_heartrate_option": true,
      "elev_high": 102.6,
      "elev_low": 62.4,
      "upload_id": 19912636681,
      "upload_id_str": "19912636681",
      "external_id": "4814301A-C706-4631-A7C9-3F84A338F0B5.fit",
      "from_accepted_tag": false,
      "pr_count": 0,
      "total_photo_count": 0,
      "has_kudoed": false,
      "suffer_score": 98.0
    },
    {
      "resource_state": 2,
      "athlete": {
        "id": 7234187,
        "resource_state": 1
      },
      "name": "B&B swims \ud83d\udc97\ud83c\udfca\ud83c\udffb\u200d\u2642\ufe0f\ud83e\ude72",
      "distance": 158.0,
      "moving_time": 2060,
      "elapsed_time": 2060,
      "total_elevation_gain": 3.6,
      "type": "Swim",
      "sport_type": "Swim",
      "device_name": "Apple Watch Series 9",
      "id": 18816008973,
      "start_date": "2026-06-06T21:00:18Z",
      "start_date_local": "2026-06-07T07:00:18Z",
      "timezone": "(GMT+10:00) Australia/Sydney",
      "utc_offset": 36000.0,
      "location_city": null,
      "location_state": null,
      "location_country": null,
      "achievement_count": 2,
      "kudos_count": 3,
      "comment_count": 0,
      "athlete_count": 5,
      "photo_count": 0,
      "map": {
        "id": "a18816008973",
        "summary_polyline": "blhmE__lz[]_@KWi@gAU_ACi@J]Re@HKCAd@a@b@}@^]R[N_@z@yAl@i@NGNO\\c@?ML?F}BCsBBqAB[Ek@PcB?c@A{@QS@GBLHDOCDM@HQHLB@B_@dA@TOd@CTK\\Ed@Md@E`ACRFVHp@DT?VFNDd@E|@k@rB[f@m@`BKHIPk@R_@ZUFGAA~@a@f@KPWtABr@^v@`@^",
        "resource_state": 2
      },
      "trainer": false,
      "commute": false,
      "manual": false,
      "private": false,
      "visibility": "followers_only",
      "flagged": false,
      "gear_id": null,
      "start_latlng": [
        -33.799218,
        151.290887
      ],
      "end_latlng": [
        -33.798989,
        151.291053
      ],
      "average_speed": 0.077,
      "max_speed": 6.562,
      "has_heartrate": true,
      "average_heartrate": 122.4,
      "max_heartrate": 139.0,
      "heartrate_opt_out": false,
      "display_hide_heartrate_option": true,
      "elev_high": 9.8,
      "elev_low": -2.0,
      "upload_id": 19926770169,
      "upload_id_str": "19926770169",
      "external_id": "56AD04D6-8E63-4931-B376-A335AAAB44D3.fit",
      "from_accepted_tag": false,
      "pr_count": 2,
      "total_photo_count": 0,
      "has_kudoed": false,
      "suffer_score": 1.0
    },
    {
      "resource_state": 2,
      "athlete": {
        "id": 7234187,
        "resource_state": 1
      },
      "name": "Balmoral Buoys and Island \ud83d\udedf\ud83c\udfdd\ufe0f\ud83c\udfca\ud83c\udffb\u200d\u2642\ufe0f\ud83e\ude72",
      "distance": 1223.6,
      "moving_time": 2038,
      "elapsed_time": 2038,
      "total_elevation_gain": 18.0,
      "type": "Swim",
      "sport_type": "Swim",
      "device_name": "Apple Watch Series 9",
      "id": 18842465024,
      "start_date": "2026-06-07T21:39:14Z",
      "start_date_local": "2026-06-08T07:39:14Z",
      "timezone": "(GMT+10:00) Australia/Sydney",
      "utc_offset": 36000.0,
      "location_city": null,
      "location_state": null,
      "location_country": null,
      "achievement_count": 0,
      "kudos_count": 3,
      "comment_count": 0,
      "athlete_count": 3,
      "photo_count": 0,
      "map": {
        "id": "a18842465024",
        "summary_polyline": "nzmmEcodz[GCe@YYGU?e@De@AYFYNe@D]N{@UkAN_@HSAUDUFs@D_@QES_@_@O]SW[Ua@a@QM[M]CM@SLWAOFQ^Yv@Ib@RYPo@Zu@FEb@AJBp@^^JTNHLJVRNPb@RVHBVVNCFB?CAD@E`@Kr@@z@Eb@GbCMj@Mb@?n@Ip@Lb@B\\AJG",
        "resource_state": 2
      },
      "trainer": false,
      "commute": false,
      "manual": false,
      "private": false,
      "visibility": "followers_only",
      "flagged": false,
      "gear_id": null,
      "start_latlng": [
        -33.827115,
        151.252507
      ],
      "end_latlng": [
        -33.827056,
        151.252607
      ],
      "average_speed": 0.6,
      "max_speed": 4.355,
      "has_heartrate": true,
      "average_heartrate": 99.5,
      "max_heartrate": 130.0,
      "heartrate_opt_out": false,
      "display_hide_heartrate_option": true,
      "elev_high": 5.8,
      "elev_low": -1.0,
      "upload_id": 19953712682,
      "upload_id_str": "19953712682",
      "external_id": "AA102B90-A053-4F62-8F2B-40D61987C453.fit",
      "from_accepted_tag": false,
      "pr_count": 0,
      "total_photo_count": 0,
      "has_kudoed": false,
      "suffer_score": 5.0
    },
    {
      "resource_state": 2,
      "athlete": {
        "id": 7234187,
        "resource_state": 1
      },
      "name": "Prince Alfred \ud83e\udd34\ud83c\udfca\ud83c\udffb\u200d\u2642\ufe0f\ud83e\ude72",
      "distance": 2000.0,
      "moving_time": 2566,
      "elapsed_time": 2566,
      "total_elevation_gain": 0,
      "type": "Swim",
      "sport_type": "Swim",
      "device_name": "Apple Watch Series 9",
      "id": 18842465137,
      "start_date": "2026-06-08T20:04:32Z",
      "start_date_local": "2026-06-09T06:04:32Z",
      "timezone": "(GMT+10:00) Antarctica/DumontDUrville",
      "utc_offset": 36000.0,
      "location_city": null,
      "location_state": null,
      "location_country": null,
      "achievement_count": 0,
      "kudos_count": 2,
      "comment_count": 0,
      "athlete_count": 1,
      "photo_count": 0,
      "map": {
        "id": "a18842465137",
        "summary_polyline": "",
        "resource_state": 2
      },
      "trainer": true,
      "commute": false,
      "manual": false,
      "private": false,
      "visibility": "followers_only",
      "flagged": false,
      "gear_id": null,
      "start_latlng": [],
      "end_latlng": [],
      "average_speed": 0.779,
      "max_speed": 8.333,
      "has_heartrate": true,
      "average_heartrate": 139.7,
      "max_heartrate": 167.0,
      "heartrate_opt_out": false,
      "display_hide_heartrate_option": true,
      "elev_high": 0.0,
      "elev_low": 0.0,
      "upload_id": 19953712841,
      "upload_id_str": "19953712841",
      "external_id": "ACF3F93E-59D7-46CF-A054-76767233BF83.fit",
      "from_accepted_tag": false,
      "pr_count": 0,
      "total_photo_count": 0,
      "has_kudoed": false,
      "suffer_score": 81.0
    },
    {
      "resource_state": 2,
      "athlete": {
        "id": 7234187,
        "resource_state": 1
      },
      "name": "Morning Swim",
      "distance": 2000.0,
      "moving_time": 2508,
      "elapsed_time": 2508,
      "total_elevation_gain": 0,
      "type": "Swim",
      "sport_type": "Swim",
      "device_name": "Apple Watch Series 9",
      "id": 18895778701,
      "start_date": "2026-06-09T20:08:33Z",
      "start_date_local": "2026-06-10T06:08:33Z",
      "timezone": "(GMT+10:00) Antarctica/DumontDUrville",
      "utc_offset": 36000.0,
      "location_city": null,
      "location_state": null,
      "location_country": null,
      "achievement_count": 0,
      "kudos_count": 1,
      "comment_count": 0,
      "athlete_count": 1,
      "photo_count": 0,
      "map": {
        "id": "a18895778701",
        "summary_polyline": "",
        "resource_state": 2
      },
      "trainer": true,
      "commute": false,
      "manual": false,
      "private": false,
      "visibility": "followers_only",
      "flagged": false,
      "gear_id": null,
      "start_latlng": [],
      "end_latlng": [],
      "average_speed": 0.797,
      "max_speed": 10.0,
      "has_heartrate": true,
      "average_heartrate": 138.2,
      "max_heartrate": 175.0,
      "heartrate_opt_out": false,
      "display_hide_heartrate_option": true,
      "elev_high": 0.0,
      "elev_low": 0.0,
      "upload_id": 20007887432,
      "upload_id_str": "20007887432",
      "external_id": "650EC030-3100-4406-BE11-AACEE3F21A1D.fit",
      "from_accepted_tag": false,
      "pr_count": 0,
      "total_photo_count": 0,
      "has_kudoed": false,
      "suffer_score": 82.0
    },
    {
      "resource_state": 2,
      "athlete": {
        "id": 7234187,
        "resource_state": 1
      },
      "name": "Balmoral Buoys \ud83d\udedf\ud83e\ude72\ud83c\udfca\ud83c\udffb\u200d\u2642\ufe0f",
      "distance": 998.9,
      "moving_time": 1625,
      "elapsed_time": 1625,
      "total_elevation_gain": 21.0,
      "type": "Swim",
      "sport_type": "Swim",
      "device_name": "Apple Watch Series 9",
      "id": 18895778901,
      "start_date": "2026-06-11T20:56:06Z",
      "start_date_local": "2026-06-12T06:56:06Z",
      "timezone": "(GMT+10:00) Australia/Sydney",
      "utc_offset": 36000.0,
      "location_city": null,
      "location_state": null,
      "location_country": null,
      "achievement_count": 0,
      "kudos_count": 2,
      "comment_count": 0,
      "athlete_count": 2,
      "photo_count": 0,
      "map": {
        "id": "a18895778901",
        "summary_polyline": "~zmmEiodz[CA?Cg@IeAI_@?aAB_CVk@BuANm@Bo@F_@AIHECABp@ShAKf@QvB?A@k@WU?iAJw@Vi@GVBl@?rAMt@QvB@h@Q|AHn@NP?HDBAxA^",
        "resource_state": 2
      },
      "trainer": false,
      "commute": false,
      "manual": false,
      "private": false,
      "visibility": "followers_only",
      "flagged": false,
      "gear_id": null,
      "start_latlng": [
        -33.8272,
        151.252538
      ],
      "end_latlng": [
        -33.827513,
        151.252459
      ],
      "average_speed": 0.615,
      "max_speed": 5.051,
      "has_heartrate": true,
      "average_heartrate": 97.6,
      "max_heartrate": 122.0,
      "heartrate_opt_out": false,
      "display_hide_heartrate_option": true,
      "elev_high": 7.2,
      "elev_low": -1.0,
      "upload_id": 20007887571,
      "upload_id_str": "20007887571",
      "external_id": "440B3234-3F67-44C9-8174-167C0D3FF30C.fit",
      "from_accepted_tag": false,
      "pr_count": 0,
      "total_photo_count": 0,
      "has_kudoed": false,
      "suffer_score": 3.0
    },
    {
      "resource_state": 2,
      "athlete": {
        "id": 7234187,
        "resource_state": 1
      },
      "name": "Zoo run \ud83c\udfc3\ud83c\udffb\u200d\u2642\ufe0f\ud83e\udd92\ud83e\udd81",
      "distance": 13720.2,
      "moving_time": 4564,
      "elapsed_time": 4963,
      "total_elevation_gain": 126.2,
      "type": "Run",
      "sport_type": "Run",
      "workout_type": null,
      "device_name": "Apple Watch Series 9",
      "id": 18895779266,
      "start_date": "2026-06-12T20:31:41Z",
      "start_date_local": "2026-06-13T06:31:41Z",
      "timezone": "(GMT+10:00) Australia/Sydney",
      "utc_offset": 36000.0,
      "location_city": null,
      "location_state": null,
      "location_country": null,
      "achievement_count": 0,
      "kudos_count": 6,
      "comment_count": 0,
      "athlete_count": 3,
      "photo_count": 0,
      "map": {
        "id": "a18895779266",
        "summary_polyline": "rlnmEub~y[AVDRHJVJJH?Ri@hBc@hAm@nCi@xBu@hIGXe@dAIf@Gx@AjA?j@BZJZT`@RTLFn@NJRN?LHHHDX?VWx@Kl@s@jJOtAGjA?RLZd@h@VRx@\\vBXjBF~B`@vEl@fA^fBTfBPdARn@@JHMlAEtAOvCGj@ENMJoDzAO@sB[mBOgA_@k@MiBQiAGuAMgAU_AIa@K}ASq@M[?ICAE?a@ZaJLm@JOTULER?dAZr@L`CRd@HLFZ_@VCv@HjBXfALpATX?LCBGBQH{BNeBPwA@SAIUMs@Og@Eg@BWIyCqB_Ai@eDyBQSQ[KUS}@i@cACODSOOSIUOq@MUOOYK]Io@AwAHiBNeAX{@BQ`@qFJeANk@b@sAViAp@wBb@mAJa@?QM}CB]Lo@N}BL]RIR@`ARH?FIJ[ZaB^uADq@Bu@A_@Qw@[}Bu@gEK[k@mAc@o@Sa@e@oACM@SC[Gc@_@wAWo@s@}@uB_CkAqBcB_Fe@aBYq@iAsAu@s@y@{@e@_@IKCIHBVR?@WSkBoByBuBY[}@}AaAyBu@uBKg@M_AK{BCyBFmAAyBB}BEg@AmBH{CAQCOEGMGmAa@q@OQ@WHG@}@ScAKhARfD`@NDXLJBV@PCDGD[DaBJ[P{@rCsHh@iBTc@NMXMp@Qd@Kr@If@ChAWfCCZKRAfA?`BEVBPLdEYt@Ml@GpCK\\@t@LpA`@dAJnB`@v@JpCb@hBLl@?T@~Cj@nCVnDf@x@DpCXhATtBPdCZ|ATt@NN?JGDG?GGGeAI_@A{@IaC_@sBUg@IkFk@sB[cI}@iEk@qE_@iB_@qBWM@ONKD_CMWLWSYEeCFc@Fo@@e@Dc@AODQLIf@EDMMKWSIO?eAHSGu@?I@IH[zCQ|@GfBc@~FCbA@NDFb@P`C\\FJ@TSbDUxBShDGh@Ab@WfEOrAo@hECj@aA~MKd@]l@ON@CGXBJHNhAfApApBt@~AXz@`@x@v@lBx@pCn@~@tAbBX^LZ`@fA\\pAZd@dAvC`@|AbAxCt@jDRj@Fj@Bj@GzAKb@Sl@_@rAOZSLQAg@MSCMBIHGPQz@e@hBK`A",
        "resource_state": 2
      },
      "trainer": false,
      "commute": false,
      "manual": false,
      "private": false,
      "visibility": "followers_only",
      "flagged": false,
      "gear_id": null,
      "start_latlng": [
        -33.83002,
        151.219793
      ],
      "end_latlng": [
        -33.830133,
        151.220097
      ],
      "average_speed": 3.006,
      "max_speed": 4.273,
      "has_heartrate": true,
      "average_heartrate": 158.7,
      "max_heartrate": 183.0,
      "heartrate_opt_out": false,
      "display_hide_heartrate_option": true,
      "elev_high": 95.6,
      "elev_low": 59.6,
      "upload_id": 20007887879,
      "upload_id_str": "20007887879",
      "external_id": "0E00E922-9A11-42F1-8C87-31994C2F33B2.fit",
      "from_accepted_tag": false,
      "pr_count": 0,
      "total_photo_count": 0,
      "has_kudoed": false,
      "suffer_score": 184.0
    }
  ]
}